README.md
setup.py
solat/__init__.py
solat.egg-info/PKG-INFO
solat.egg-info/SOURCES.txt
solat.egg-info/dependency_links.txt
solat.egg-info/not-zip-safe
solat.egg-info/requires.txt
solat.egg-info/top_level.txt