Metadata-Version: 1.0
Name: solat
Version: 0.1
Summary: Malaysia prayer time based on jakim XML
Home-page: https://github.com/SyafiqTermizi/waktu-solat/
Author: syafiq
Author-email: ahmadsyafiq93@gmail.com
License: UNKNOWN
Platform: UNKNOWN
